LICENSE
setup.py
webcheck/__init__.py
webcheck/__main__.py
webcheck_strings.egg-info/PKG-INFO
webcheck_strings.egg-info/SOURCES.txt
webcheck_strings.egg-info/dependency_links.txt
webcheck_strings.egg-info/entry_points.txt
webcheck_strings.egg-info/top_level.txt