Metadata-Version: 2.1
Name: webcheck-strings
Version: 1.608
Summary: Monitor text strings on websites
Home-page: http://ssb22.user.srcf.net/setup/webcheck.html
Author: Silas S. Brown
Author-email: ssb22@cam.ac.uk
License: Apache 2
Platform: any
Classifier: Programming Language :: Python :: 2
Classifier: Programming Language :: Python :: 3
Classifier: License :: OSI Approved :: Apache Software License
Classifier: Operating System :: OS Independent
Requires-Python: >=2.3
License-File: LICENSE
